setup.py
qtapi2/__init__.py
qtapi2/core.py
qtapi2/moduleproxy.py
qtapi2.egg-info/PKG-INFO
qtapi2.egg-info/SOURCES.txt
qtapi2.egg-info/dependency_links.txt
qtapi2.egg-info/requires.txt
qtapi2.egg-info/top_level.txt