Metadata-Version: 1.1
Name: qtapi2
Version: 1.0.0
Summary: Simplifying wrapper around Qt.py.
Home-page: https://github.com/vfxetc/qtapi2
Author: Mike Boers
Author-email: floss+qtapi2@vfxetc.com
License: BSD-3
Platform: UNKNOWN
Classifier: Intended Audience :: Developers
Classifier: License :: OSI Approved :: BSD License
Classifier: Natural Language :: English
Classifier: Operating System :: OS Independent
Classifier: Programming Language :: Python :: 2
Classifier: Topic :: Software Development :: Libraries :: Python Modules
